<?xml version="1.0" encoding="UTF-8" ?>
<!DOCTYPE mapper PUBLIC "-//mybatis.org//DTD Mapper 3.0//EN" "http://mybatis.org/dtd/mybatis-3-mapper.dtd" >
<mapper namespace="rest.mybatis.dao.passDao.PaasTemplateMapper" >
  <resultMap id="BaseResultMap" type="rest.mybatis.model.passModel.PaasTemplate" >
    <!--
      WARNING - @mbggenerated
      This element is automatically generated by MyBatis Generator, do not modify.
      This element was generated on Mon May 08 16:50:01 CST 2017.
    -->
    <id column="ID" property="id" jdbcType="INTEGER" />
    <result column="TEMPLATE_ID" property="templateId" jdbcType="VARCHAR" />
    <result column="VERSION" property="version" jdbcType="VARCHAR" />
    <result column="TEMPLATE_TYPE" property="templateType" jdbcType="VARCHAR" />
    <result column="TEMPLATE_CATEGORY" property="templateCategory" jdbcType="VARCHAR" />
    <result column="USER_MODE" property="userMode" jdbcType="VARCHAR" />
    <result column="PRICE" property="price" jdbcType="DOUBLE" />
    <result column="IS_PUB" property="isPub" jdbcType="INTEGER" />
    <result column="UPLOADPERSON" property="uploadPerson" jdbcType="VARCHAR" />
    <result column="UPLOADDATE" property="uploadDate" jdbcType="DATE" />
    <result column="PRODUCT_NAME" property="productName" jdbcType="VARCHAR" />
    <collection property="paasSubservices" column="ID" ofType="rest.mybatis.model.passModel.PaasSubservice" select="selectSubserviceBytempleteId"></collection>
  </resultMap>
  <resultMap id="PaasTempleateResultMap" type="rest.mybatis.model.passModel.PaasTemplate" >
    <!--
      WARNING - @mbggenerated
      This element is automatically generated by MyBatis Generator, do not modify.
      This element was generated on Mon May 08 16:50:01 CST 2017.
    -->
    <id column="ID" property="id" jdbcType="INTEGER" />
    <result column="TEMPLATE_ID" property="templateId" jdbcType="VARCHAR" />
    <result column="VERSION" property="version" jdbcType="VARCHAR" />
    <result column="TEMPLATE_TYPE" property="templateType" jdbcType="VARCHAR" />
    <result column="TEMPLATE_CATEGORY" property="templateCategory" jdbcType="VARCHAR" />
    <result column="USER_MODE" property="userMode" jdbcType="VARCHAR" />
    <result column="PRICE" property="price" jdbcType="DOUBLE" />
    <result column="IS_PUB" property="isPub" jdbcType="INTEGER" />
    <result column="TEMPLATE_NAME" property="templateName" jdbcType="LONGVARCHAR" />
  </resultMap>
  <resultMap type="java.lang.String" id="CateGoryMap">
  	<result column="TEMPLATE_CATEGORY" property="templateCategory" jdbcType="VARCHAR" />
  </resultMap>
  <resultMap type="java.lang.String" id="UserModeMap">
  	 <result column="USER_MODE" property="userMode" jdbcType="VARCHAR" />
  </resultMap>
  <resultMap id="ResultMapWithBLOBs" type="rest.mybatis.model.passModel.PaasTemplate" extends="BaseResultMap" >
    <!--
      WARNING - @mbggenerated
      This element is automatically generated by MyBatis Generator, do not modify.
      This element was generated on Mon May 08 16:50:01 CST 2017.
    -->
    <result column="TEMPLATE_NAME" property="templateName" jdbcType="LONGVARCHAR" />
  </resultMap>
  <sql id="Base_Column_List" >
    <!--
      WARNING - @mbggenerated
      This element is automatically generated by MyBatis Generator, do not modify.
      This element was generated on Mon May 08 16:50:01 CST 2017.
    -->
    ID, TEMPLATE_ID, VERSION, TEMPLATE_TYPE, TEMPLATE_CATEGORY, USER_MODE, PRICE, IS_PUB,UPLOADPERSON,UPLOADDATE,PRODUCT_NAME
  </sql>
  <sql id="Blob_Column_List" >
    <!--
      WARNING - @mbggenerated
      This element is automatically generated by MyBatis Generator, do not modify.
      This element was generated on Mon May 08 16:50:01 CST 2017.
    -->
    TEMPLATE_NAME
  </sql>
  <!-- 子查询模块列表 -->
  <select id="selectSubserviceBytempleteId" parameterType="java.lang.Integer" resultMap="rest.mybatis.dao.passDao.PaasSubserviceMapper.BaseResultMap">
  	  select ID, TEMPLATE_ID, MODULE_NAME, MODULE_URL, MODULE_IS_DIS, MODULE_DES, MODULE_IMG_NAME
  	   from PAAS_SUBSERVICE
  	   where TEMPLATE_ID=#{ID}
  </select>
  <select id="selectByPrimaryKey" resultMap="ResultMapWithBLOBs" parameterType="java.lang.Integer" >
    <!--
      WARNING - @mbggenerated
      This element is automatically generated by MyBatis Generator, do not modify.
      This element was generated on Mon May 08 16:50:01 CST 2017.
    -->
    select 
    <include refid="Base_Column_List" />
    ,
    <include refid="Blob_Column_List" />
    from PAAS_TEMPLATE
    where ID = #{id,jdbcType=INTEGER}
  </select>
  <select id="selectByTemplateId" resultMap="ResultMapWithBLOBs" parameterType="java.lang.String" >
    <!--
      WARNING - @mbggenerated
      This element is automatically generated by MyBatis Generator, do not modify.
      This element was generated on Mon May 08 16:50:01 CST 2017.
    -->
    select 
    <include refid="Base_Column_List" />
    ,
    <include refid="Blob_Column_List" />
    from PAAS_TEMPLATE
    where ID = #{id,jdbcType=VARCHAR}
  </select>
  <select id="selectByTemplateIdConfig" resultMap="ResultMapWithBLOBs" parameterType="java.lang.String" >
    <!--
      WARNING - @mbggenerated
      This element is automatically generated by MyBatis Generator, do not modify.
      This element was generated on Mon May 08 16:50:01 CST 2017.
    -->
    select 
    <include refid="Base_Column_List" />
    ,
    <include refid="Blob_Column_List" />
    from PAAS_TEMPLATE
    where TEMPLATE_ID = #{templateId,jdbcType=VARCHAR}
  </select>
  
  <!-- 查询模板类别 -->
  <select id="obtainTemplateCategory" resultType="java.lang.String"  >
    <!--
      WARNING - @mbggenerated
      This element is automatically generated by MyBatis Generator, do not modify.
      This element was generated on Mon May 08 16:50:01 CST 2017.
    -->
    select 
    TEMPLATE_CATEGORY
    from PAAS_TEMPLATE
    where TEMPLATE_ID IS NOT NULL GROUP BY TEMPLATE_CATEGORY
  </select>
  
  <!-- 查询所有模板 -->
  <select id="obtainTemplateList" resultMap="ResultMapWithBLOBs" >
    
    select 
    <include refid="Base_Column_List" />
    ,
    <include refid="Blob_Column_List" />
    from PAAS_TEMPLATE
    <where>
    	TEMPLATE_ID IS NOT NULL
    	<if test="templateName != null">
    	 	AND TEMPLATE_NAME LIKE CONCAT(CONCAT('%',#{templateName}),'%')
    	</if>
    	<if test="templateCategory != null">
    		AND TEMPLATE_CATEGORY = #{templateCategory}
    	</if>
    </where> 
     ORDER BY ID DESC
  </select>
  <!-- 查询产品列表动态条件 -->
  <select id="selectpaasTemplateList" resultMap="ResultMapWithBLOBs" parameterType="java.lang.Integer" >
  <bind name="offset" value="(page-1)*counm"/>
    <!--
      WARNING - @mbggenerated
      This element is automatically generated by MyBatis Generator, do not modify.
      This element was generated on Mon May 08 16:50:01 CST 2017.
    -->
    select 
    <include refid="Base_Column_List" />
    ,
    <include refid="Blob_Column_List" />
    from PAAS_TEMPLATE
    <where>
    	IS_PUB = 1
    	<if test="productName!=null and productName!=''">
    	and PRODUCT_NAME  like '%${productName}%'
    	</if>
    	<if test="templateCategory!=null and templateCategory!=''">
    	and TEMPLATE_CATEGORY = #{templateCategory}
    	</if>
    	<if test="id!=null and id!=''">
    	and ID = #{id}
    	</if>
    	order by ID desc
		limit ${offset},${counm}
    </where>
  </select>
  <!--提取分类  -->
	 <select id="selecttemplateCategory" resultMap="ResultMapWithBLOBs" >
    <!--
      WARNING - @mbggenerated
      This element is automatically generated by MyBatis Generator, do not modify.
      This element was generated on Mon May 08 16:50:01 CST 2017.
    -->
    select 
    <include refid="Base_Column_List" />
    ,
    <include refid="Blob_Column_List" />
    from PAAS_TEMPLATE group by TEMPLATE_CATEGORY
  </select>
  <!-- 数据条数 -->
  <select id="selecttemplateCount" resultType="java.lang.Integer">
    <!--
      WARNING - @mbggenerated
      This element is automatically generated by MyBatis Generator, do not modify.
      This element was generated on Mon May 08 16:50:01 CST 2017.
    -->
    select 
   count(*)
    from PAAS_TEMPLATE
     <where>
    	IS_PUB = 1
    	<if test="productName!=null and productName!=''">
    	and PRODUCT_NAME  like '%${productName}%'
    	</if>
    	<if test="templateCategory!=null and templateCategory!=''">
    	and TEMPLATE_CATEGORY = #{templateCategory}
    	</if>
    	<if test="id!=null and id!=''">
    	and ID = #{id}
    	</if>
    </where>
  </select>
  <delete id="deleteByPrimaryKey" parameterType="java.lang.Integer" >
    <!--
      WARNING - @mbggenerated
      This element is automatically generated by MyBatis Generator, do not modify.
      This element was generated on Mon May 08 16:50:01 CST 2017.
    -->
    delete from PAAS_TEMPLATE
    where ID = #{id,jdbcType=INTEGER}
  </delete>
  <insert id="insert" useGeneratedKeys="true" keyProperty="id" parameterType="rest.mybatis.model.passModel.PaasTemplate" >
    <!--
      WARNING - @mbggenerated
      This element is automatically generated by MyBatis Generator, do not modify.
      This element was generated on Mon May 08 16:50:01 CST 2017.
    -->
    insert into PAAS_TEMPLATE (ID, TEMPLATE_ID, VERSION, 
      TEMPLATE_TYPE, TEMPLATE_CATEGORY, USER_MODE, 
      PRICE, IS_PUB, TEMPLATE_NAME,UPLOADPERSON,UPLOADDATE,PRODUCT_NAME
      )
    values (#{id,jdbcType=INTEGER}, #{templateId,jdbcType=VARCHAR}, #{version,jdbcType=VARCHAR}, 
      #{templateType,jdbcType=VARCHAR}, #{templateCategory,jdbcType=VARCHAR}, #{userMode,jdbcType=VARCHAR}, 
      #{price,jdbcType=DOUBLE}, #{isPub,jdbcType=INTEGER}, #{templateName,jdbcType=LONGVARCHAR},#{uploadPerson,jdbcType=VARCHAR},
      #{uploadDate,jdbcType=DATE},#{productName,jdbcType=VARCHAR}
      )
  </insert>
  <insert id="insertSelective" parameterType="rest.mybatis.model.passModel.PaasTemplate" >
    <!--
      WARNING - @mbggenerated
      This element is automatically generated by MyBatis Generator, do not modify.
      This element was generated on Mon May 08 16:50:01 CST 2017.
    -->
    insert into PAAS_TEMPLATE
    <trim prefix="(" suffix=")" suffixOverrides="," >
      <if test="id != null" >
        ID,
      </if>
      <if test="templateId != null" >
        TEMPLATE_ID,
      </if>
      <if test="version != null" >
        VERSION,
      </if>
      <if test="templateType != null" >
        TEMPLATE_TYPE,
      </if>
      <if test="templateCategory != null" >
        TEMPLATE_CATEGORY,
      </if>
      <if test="userMode != null" >
        USER_MODE,
      </if>
      <if test="price != null" >
        PRICE,
      </if>
      <if test="isPub != null" >
        IS_PUB,
      </if>
      <if test="templateName != null" >
        TEMPLATE_NAME,
      </if>
    </trim>
    <trim prefix="values (" suffix=")" suffixOverrides="," >
      <if test="id != null" >
        #{id,jdbcType=INTEGER},
      </if>
      <if test="templateId != null" >
        #{templateId,jdbcType=VARCHAR},
      </if>
      <if test="version != null" >
        #{version,jdbcType=VARCHAR},
      </if>
      <if test="templateType != null" >
        #{templateType,jdbcType=VARCHAR},
      </if>
      <if test="templateCategory != null" >
        #{templateCategory,jdbcType=VARCHAR},
      </if>
      <if test="userMode != null" >
        #{userMode,jdbcType=VARCHAR},
      </if>
      <if test="price != null" >
        #{price,jdbcType=DOUBLE},
      </if>
      <if test="isPub != null" >
        #{isPub,jdbcType=INTEGER},
      </if>
      <if test="templateName != null" >
        #{templateName,jdbcType=LONGVARCHAR},
      </if>
    </trim>
  </insert>
  <update id="updateByPrimaryKeySelective" parameterType="rest.mybatis.model.passModel.PaasTemplate" >
    <!--
      WARNING - @mbggenerated
      This element is automatically generated by MyBatis Generator, do not modify.
      This element was generated on Mon May 08 16:50:01 CST 2017.
    -->
    update PAAS_TEMPLATE
    <set >
      <if test="templateId != null" >
        TEMPLATE_ID = #{templateId,jdbcType=VARCHAR},
      </if>
      <if test="version != null" >
        VERSION = #{version,jdbcType=VARCHAR},
      </if>
      <if test="templateType != null" >
        TEMPLATE_TYPE = #{templateType,jdbcType=VARCHAR},
      </if>
      <if test="templateCategory != null" >
        TEMPLATE_CATEGORY = #{templateCategory,jdbcType=VARCHAR},
      </if>
      <if test="userMode != null" >
        USER_MODE = #{userMode,jdbcType=VARCHAR},
      </if>
      <if test="price != null" >
        PRICE = #{price,jdbcType=DOUBLE},
      </if>
      <if test="isPub != null" >
        IS_PUB = #{isPub,jdbcType=INTEGER},
      </if>
      <if test="templateName != null" >
        TEMPLATE_NAME = #{templateName,jdbcType=LONGVARCHAR},
      </if>
      <if test="uploadPerson != null" >
        UPLOADPERSON = #{uploadPerson,jdbcType=VARCHAR},
      </if>
      <if test="uploadDate != null" >
       UPLOADDATE = #{uploadDate,jdbcType=DATE},
      </if>
      <if test="productName != null" >
        PRODUCT_NAME = #{productName,jdbcType=VARCHAR},
      </if>
    </set>
    where ID = #{id,jdbcType=INTEGER}
  </update>
  <update id="updateByPrimaryKeyWithBLOBs" parameterType="rest.mybatis.model.passModel.PaasTemplate" >
    <!--
      WARNING - @mbggenerated
      This element is automatically generated by MyBatis Generator, do not modify.
      This element was generated on Mon May 08 16:50:01 CST 2017.
    -->
    update PAAS_TEMPLATE
    set TEMPLATE_ID = #{templateId,jdbcType=VARCHAR},
      VERSION = #{version,jdbcType=VARCHAR},
      TEMPLATE_TYPE = #{templateType,jdbcType=VARCHAR},
      TEMPLATE_CATEGORY = #{templateCategory,jdbcType=VARCHAR},
      USER_MODE = #{userMode,jdbcType=VARCHAR},
      PRICE = #{price,jdbcType=DOUBLE},
      IS_PUB = #{isPub,jdbcType=INTEGER},
      TEMPLATE_NAME = #{templateName,jdbcType=LONGVARCHAR}
    where ID = #{id,jdbcType=INTEGER}
  </update>
  <update id="updateByPrimaryKey" parameterType="rest.mybatis.model.passModel.PaasTemplate" >
    <!--
      WARNING - @mbggenerated
      This element is automatically generated by MyBatis Generator, do not modify.
      This element was generated on Mon May 08 16:50:01 CST 2017.
    -->
    update PAAS_TEMPLATE
    set TEMPLATE_ID = #{templateId,jdbcType=VARCHAR},
      VERSION = #{version,jdbcType=VARCHAR},
      TEMPLATE_TYPE = #{templateType,jdbcType=VARCHAR},
      TEMPLATE_CATEGORY = #{templateCategory,jdbcType=VARCHAR},
      USER_MODE = #{userMode,jdbcType=VARCHAR},
      PRICE = #{price,jdbcType=DOUBLE},
      IS_PUB = #{isPub,jdbcType=INTEGER}
    where ID = #{id,jdbcType=INTEGER}
  </update>
    <select id="selectPaasTemplateByCondit" resultType="java.lang.Integer" parameterType="rest.mybatis.model.passModel.PaasTemplate">
  	select count(id) from PAAS_TEMPLATE
    where 1=1 
    <if test="templateName!= null and templateName != ''">
     and TEMPLATE_NAME like CONCAT('%',#{templateName},'%')
    </if>
    <if test="isPub != null">
     and IS_PUB=#{isPub} 
    </if> 
    <if test="userMode!= null  and userMode!=''">
     and USER_MODE=#{userMode}
    </if>
  </select>
  
  <select id="selectPaasTemplateObjByCondit" resultMap="PaasTempleateResultMap" parameterType="rest.page.util.Pageinfo">
  	select
  	<include refid="Base_Column_List" />
    ,
    <include refid="Blob_Column_List" />
    from PAAS_TEMPLATE
    where 1=1 
    <if test="ConditionObj.templateName!= null and ConditionObj.templateName != ''">
     and TEMPLATE_NAME like CONCAT('%',#{ConditionObj.templateName},'%')
    </if>
    <if test="ConditionObj.isPub != null">
     and IS_PUB=#{ConditionObj.isPub} 
    </if> 
    <if test="ConditionObj.userMode!= null and ConditionObj.userMode!=''">
     and USER_MODE=#{ConditionObj.userMode}
    </if>
    order by TEMPLATE_NAME
    limit #{begin},#{shownum}
  </select>
  
  <update id="UpdateProduct" parameterType="rest.mybatis.model.passModel.PaasTemplate">
  	update PAAS_TEMPLATE
    <set >
      <if test="templateId != null" >
        TEMPLATE_ID = #{templateId,jdbcType=VARCHAR},
      </if>
      <if test="version != null" >
        VERSION = #{version,jdbcType=VARCHAR},
      </if>
      <if test="templateType != null" >
        TEMPLATE_TYPE = #{templateType,jdbcType=VARCHAR},
      </if>
      <if test="templateCategory != null" >
        TEMPLATE_CATEGORY = #{templateCategory,jdbcType=VARCHAR},
      </if>
      <if test="isPub != null" >
        IS_PUB = #{isPub,jdbcType=INTEGER},
      </if>
      <if test="templateName != null" >
        TEMPLATE_NAME = #{templateName,jdbcType=LONGVARCHAR},
      </if>
    </set>
    where ID = #{id,jdbcType=INTEGER}
  </update>
  
  <select id="selectCategory" resultMap="CateGoryMap">
  	 select DISTINCT TEMPLATE_CATEGORY from PAAS_TEMPLATE
  </select>
  <select id="selectUserMode" resultMap="UserModeMap">
  	 select DISTINCT USER_MODE from PAAS_TEMPLATE
  </select>
  
  <select id="selectByid" resultMap="PaasTempleateResultMap" parameterType="java.lang.Integer">
  	select 
  	<include refid="Base_Column_List" /> 
  	from PAAS_TEMPLATE
  	where ID=#{id,jdbcType=INTEGER}
  </select>
</mapper>